01-led/rtl/led_blink.v
module led_blink (
    input  wire clk,
    input  wire rst_n,
    output reg  led
);

    parameter TARGET_COUNT = 9;
    reg [31:0] counter;

    always @(posedge clk or negedge rst_n) begin
        if (!rst_n) begin
            counter <= 0;
            led <= 0;
        end else begin
            if (counter == TARGET_COUNT) begin
                counter <= 0;
                led <= ~led;
            end else begin
                counter <= counter + 1;
            end
        end
    end

endmodule

01-led/tb/led_blink_tb.v
`timescale 1ns/1ps

module led_blink_tb;

	reg clk;
	reg rst_n;
	wire led;

	led_blink dut (
		.clk  (clk),
		.rst_n(rst_n),
		.led  (led)
	);

	always #5 clk = ~clk;

	initial begin
		$dumpfile("sim/led_blink.vcd");
		$dumpvars(0, led_blink_tb);

		clk   = 1'b0;
		rst_n = 1'b1;

		#1;
		rst_n = 1'b0;

		#1;
		if (led !== 1'b0) begin
			$display("ERROR: LED is not off during reset");
			$finish;
		end

		#11;
		rst_n = 1'b1;
		repeat (10) @(posedge clk);
		#1;
		if (led !== 1'b1) begin
			$display("ERROR: LED did not toggle after 10 clocks");
			$finish;
		end

		repeat (10) @(posedge clk);
		#1;
		if (led !== 1'b0) begin
			$display("ERROR: LED did not toggle back after 10 clocks");
			$finish;
		end

		$display("PASS: LED blink behavior is correct");
		$finish;
	end

endmodule

01-led/sim/led_blink.vcd
$date
	Fri Oct  2 08:39:59 2026
$end
$version
	Icarus Verilog
$end
$timescale
	1ps
$end
$scope module led_blink_tb $end
$var wire 1 ! led $end
$var reg 1 " clk $end
$var reg 1 # rst_n $end
$scope module dut $end
$var wire 1 " clk $end
$var wire 1 # rst_n $end
$var reg 32 $ counter [31:0] $end
$var reg 1 ! led $end
$upscope $end
$upscope $end
$enddefinitions $end
#0
$dumpvars
bx $
1#
0"
x!
$end
#1000
0!
b0 $
0#
#5000
1"
#10000
0"
#13000
1#
#15000
b1 $
1"
#20000
0"
#25000
b10 $
1"
#30000
0"
#35000
b11 $
1"
#40000
0"
#45000
b100 $
1"
#50000
0"
#55000
b101 $
1"
#60000
0"
#65000
b110 $
1"
#70000
0"
#75000
b111 $
1"
#80000
0"
#85000
b1000 $
1"
#90000
0"
#95000
b1001 $
1"
#100000
0"
#105000
1!
b0 $
1"
#110000
0"
#115000
b1 $
1"
#120000
0"
#125000
b10 $
1"
#130000
0"
#135000
b11 $
1"
#140000
0"
#145000
b100 $
1"
#150000
0"
#155000
b101 $
1"
#160000
0"
#165000
b110 $
1"
#170000
0"
#175000
b111 $
1"
#180000
0"
#185000
b1000 $
1"
#190000
0"
#195000
b1001 $
1"
#200000
0"
#205000
0!
b0 $
1"
